celescope/__init__.py
celescope/celescope.py
celescope/chemistry_dict.py
celescope/data/__init__.py
celescope/data/chemistry/__init__.py
celescope/data/chemistry/mobiu-1/bc1.txt
celescope/data/chemistry/mobiu-1/bc2.txt
celescope/data/chemistry/mobiu-1/bc3.txt
celescope/data/chemistry/mobiu-2/bc1.txt
celescope/data/chemistry/mobiu-2/bc2.txt
celescope/data/chemistry/mobiu-2/bc3.txt
celescope/data/chemistry/mobiu-2/linker1.txt
celescope/data/chemistry/mobiu-2/linker2.txt
celescope/data/chemistry/mobiu-2/linker3.txt
celescope/data/chemistry/mobiu_3p-1/bc1.txt
celescope/data/chemistry/mobiu_3p-1/bc2.txt
celescope/data/chemistry/mobiu_3p-1/bc3.txt
celescope/mobiu/__init__.py
celescope/mobiu/analysis.py
celescope/mobiu/convert.py
celescope/mobiu/kb_python.py
celescope/mobiu/multi_mobiu.py
celescope/rna/__init__.py
celescope/rna/analysis.py
celescope/rna/mkref.py
celescope/rna/multi_rna.py
celescope/rna/star.py
celescope/templates/css/bootstrap.min.css
celescope/templates/css/buttons.dataTables.min.css
celescope/templates/css/dataTables.jqueryui.min.css
celescope/templates/css/jquery-ui-git.css
celescope/templates/css/jquery-ui.css
celescope/templates/css/jquery.dataTables.css
celescope/templates/css/fontello-323401c3/config.json
celescope/templates/css/fontello-323401c3/css/animation.css
celescope/templates/css/fontello-323401c3/css/fontello-codes.css
celescope/templates/css/fontello-323401c3/css/fontello-embedded.css
celescope/templates/css/fontello-323401c3/css/fontello-ie7-codes.css
celescope/templates/css/fontello-323401c3/css/fontello-ie7.css
celescope/templates/css/fontello-323401c3/css/fontello.css
celescope/templates/css/fontello-323401c3/font/fontello.eot
celescope/templates/css/fontello-323401c3/font/fontello.svg
celescope/templates/css/fontello-323401c3/font/fontello.ttf
celescope/templates/css/fontello-323401c3/font/fontello.woff
celescope/templates/css/fontello-323401c3/font/fontello.woff2
celescope/templates/html/common/img1.html
celescope_mobiu-1.4.2.dist-info/licenses/LICENSE
celescope_mobiu-1.4.2.dist-info/METADATA
celescope_mobiu-1.4.2.dist-info/WHEEL
celescope_mobiu-1.4.2.dist-info/entry_points.txt
celescope_mobiu-1.4.2.dist-info/top_level.txt
celescope_mobiu-1.4.2.dist-info/RECORD
