Metadata-Version: 2.4
Name: celescope-mobiu
Version: 1.4.2
Summary: MobiuSCOPE Analysis Pipelines
Home-page: https://github.com/singleron-RD/celescope-mobiu
Author: zhouyiqi
Author-email: zhouyiqi@singleronbio.com
Classifier: Programming Language :: Python :: 3
Classifier: License :: OSI Approved :: MIT License
Classifier: Operating System :: OS Independent
Requires-Python: >=3.9
License-File: LICENSE
Requires-Dist: kb_python==0.29.1
Requires-Dist: pysam>=0.18.0
Requires-Dist: scipy==1.13.1
Requires-Dist: numpy==1.26.0
Requires-Dist: jinja2>=2.10
Requires-Dist: scikit-learn
Requires-Dist: plotly==5.24.1
Requires-Dist: plotnine==0.9.0
Requires-Dist: cython
Requires-Dist: scanpy
Requires-Dist: statsmodels
Requires-Dist: leidenalg
Requires-Dist: igraph
Requires-Dist: pandas
Requires-Dist: kaleido
Dynamic: author
Dynamic: author-email
Dynamic: classifier
Dynamic: description
Dynamic: description-content-type
Dynamic: home-page
Dynamic: license-file
Dynamic: requires-dist
Dynamic: requires-python
Dynamic: summary
